factor_analysis/__init__.py
factor_analysis/factors.py
factor_analysis/noise.py
factor_analysis/posterior.py
factor_analysis-0.0.2.dist-info/LICENSE
factor_analysis-0.0.2.dist-info/METADATA
factor_analysis-0.0.2.dist-info/WHEEL
factor_analysis-0.0.2.dist-info/top_level.txt
factor_analysis-0.0.2.dist-info/RECORD
