Metadata-Version: 2.1
Name: factor-analysis
Version: 0.0.2
Summary: Package to conduct factor analysis on data
Home-page: https://github.com/avkpy/factor-analysis
Author: Aswin Vijayakumar
Author-email: aswinkv28@gmail.com
License: UNKNOWN
Platform: UNKNOWN
Classifier: Programming Language :: Python :: 3
Classifier: License :: OSI Approved :: MIT License
Classifier: Operating System :: OS Independent
